{
  "scenario_id": "invalid_missing_permission",
  "typed_job": {
    "job_id": "job://runtime/missing-permission-001",
    "contract_id": "contract://command/local-draft-update",
    "job_type": "local_artifact_update",
    "lifecycle_state": "running",
    "runtime_adapter": "adapter://local-filesystem",
    "inputs": ["artifact://draft-before"],
    "outputs": ["artifact://draft-after"],
    "permissions": ["filesystem.read"],
    "approval_state": "not_required",
    "failure_behavior": ["stop_on_write_error"],
    "audit_events": ["audit://runtime/missing-permission-001"],
    "replay_status": "not_run"
  },
  "runtime_adapter_invocation": {
    "invocation_id": "invoke://runtime/missing-permission-001",
    "invocation_state": "executed",
    "job_id": "job://runtime/missing-permission-001",
    "adapter_id": "adapter://local-filesystem",
    "target_type": "local_file",
    "capability": "filesystem.write",
    "permission_required": "filesystem.write",
    "sandbox_mode": "workspace_write_limited",
    "impact_class": "low_impact",
    "risk_tier": "low",
    "approval_required": false,
    "approval_record": "not_required",
    "approval_scope": "not_required",
    "approval_expiry": "not_required",
    "authority_handle": "handle://runtime/missing-permission-001",
    "inputs": ["artifact://draft-before"],
    "effect_lease": "lease://runtime/missing-permission-001",
    "effect_receipt": "receipt://runtime/missing-permission-001",
    "pre_state_ref": "state://draft-before",
    "post_state_ref": "state://draft-after",
    "external_side_effects": [],
    "verification_refs": ["check://diff-reviewed"],
    "rollback_handle": "rollback://restore-draft-before",
    "irreversible_residuals": [],
    "incident_refs": [],
    "audit_refs": ["audit://runtime/missing-permission-001"],
    "residuals": [],
    "support_state_effect": "argument_only",
    "non_claims": [
      "does not execute a real filesystem write",
      "does not promote any chapter support state"
    ]
  },
  "authority_use_receipt": {
    "handle_id": "handle://runtime/missing-permission-001",
    "principal": "job://runtime/missing-permission-001",
    "purpose": "missing permission fixture",
    "destination": "local_file",
    "allowed_action": "filesystem.write",
    "clearance": "low",
    "approval_record": "not_required",
    "scif_lifecycle": ["spawn", "execute", "audit"],
    "sanitized_output": "receipt://runtime/missing-permission-001",
    "residual_leak_risk": [],
    "revocation_path": "revoke://runtime/missing-permission-001"
  },
  "non_claims": [
    "does not execute a real adapter",
    "does not promote any support state"
  ]
}
